{"openapi":"3.0.2","info":{"description":"API for proc","version":"0.4.1","title":"@datr.tech/api-proc","contact":{"email":"admin@datr-tech"},"license":{"name":"MIT","url":"https://mit-license.org/"}},"servers":[{"url":"TBC"}],"components":{"schemas":{"ProcessCreate":{"type":"object","properties":{"adminStatusId":{"default":"undefined","required":false,"type":"string","pattern":"^[0-9a-fA-F]{24}$"},"adminUserId":{"required":true,"type":"string","pattern":"^[0-9a-fA-F]{24}$"},"frameworkId":{"required":true,"type":"string","pattern":"^[0-9a-fA-F]{24}$"},"journeyId":{"required":true,"type":"string","pattern":"^[0-9a-fA-F]{24}$"}}},"ProcessUpdate":{"type":"object","properties":{"adminStatusId":{"default":"undefined","required":false,"type":"string","pattern":"^[0-9a-fA-F]{24}$"},"adminUserId":{"default":"undefined","required":false,"type":"string","pattern":"^[0-9a-fA-F]{24}$"},"frameworkId":{"default":"undefined","required":false,"type":"string","pattern":"^[0-9a-fA-F]{24}$"},"journeyId":{"default":"undefined","required":false,"type":"string","pattern":"^[0-9a-fA-F]{24}$"}}},"ProcessRead":{"type":"object","properties":{}},"ProcessDelete":{"type":"object","properties":{}},"ThreadCreate":{"type":"object","properties":{"adminStatusId":{"default":"undefined","required":false,"type":"string","pattern":"^[0-9a-fA-F]{24}$"},"adminUserId":{"required":true,"type":"string","pattern":"^[0-9a-fA-F]{24}$"},"hopId":{"required":true,"type":"string","pattern":"^[0-9a-fA-F]{24}$"},"processId":{"required":true,"type":"string","pattern":"^[0-9a-fA-F]{24}$"}}},"ThreadUpdate":{"type":"object","properties":{"adminStatusId":{"default":"undefined","required":false,"type":"string","pattern":"^[0-9a-fA-F]{24}$"},"adminUserId":{"default":"undefined","required":false,"type":"string","pattern":"^[0-9a-fA-F]{24}$"},"hopId":{"default":"undefined","required":false,"type":"string","pattern":"^[0-9a-fA-F]{24}$"},"processId":{"default":"undefined","required":false,"type":"string","pattern":"^[0-9a-fA-F]{24}$"}}},"ThreadRead":{"type":"object","properties":{}},"ThreadDelete":{"type":"object","properties":{}}}},"paths":{"/process":{"post":{"tags":["process"],"summary":"Create process","operationId":"createProcess","requestBody":{"content":{"application/json":{"schema":{"$ref":"#/components/schemas/ProcessCreate"}}}}}},"/process/:processId":{"delete":{"tags":["process"],"summary":"Delete process","operationId":"deleteProcess","parameters":[{"in":"path","name":"undefined","required":true,"schema":{"type":"string","pattern":"^[0-9a-fA-F]{24}$"}}]}},"/thread":{"post":{"tags":["thread"],"summary":"Create thread","operationId":"createThread","requestBody":{"content":{"application/json":{"schema":{"$ref":"#/components/schemas/ThreadCreate"}}}}}},"/thread/:threadId":{"delete":{"tags":["thread"],"summary":"Delete thread","operationId":"deleteThread","parameters":[{"in":"path","name":"undefined","required":true,"schema":{"type":"string","pattern":"^[0-9a-fA-F]{24}$"}}]}}}}